{
  "schema_version": 1,
  "snapshot_date": "2026-07-20",
  "source_id": "FUCHS_SOUTH_AFRICA_PRODUCT_FINDER",
  "source_url": "https://www.fuchs.com/za/en/products/service-links/product-finder/",
  "imprint_url": "https://www.fuchs.com/za/en/imprint/",
  "source_html_sha256": "fca852f812dd93c6689b6beeae84b4d1d151d5394ad34359832850f29cf3a74f",
  "imprint_html_sha256": "ed7266a55758c8ba50b29e00cac6e6a12ff66f81e9d7537f9df88b33136e60a0",
  "embedded_source_rows": 864,
  "products": 756,
  "source_series_rows_excluded": 94,
  "equipment_rows_excluded": 6,
  "placeholder_rows_excluded": 0,
  "duplicate_source_occurrences_merged": 8,
  "families": {
    "C": 23,
    "E": 3,
    "G": 187,
    "H": 47,
    "I": 44,
    "M": 50,
    "S": 54,
    "T": 73,
    "TF": 274,
    "U": 1
  },
  "brand_lines": 26,
  "compound_designation_review_rows": 23,
  "classification_basis": {
    "brand_line_and_explicit_application": 62,
    "explicit_product_line_and_application": 9,
    "explicit_product_line_and_grade": 5,
    "explicit_text": 8,
    "industrial_product_group": 41,
    "multifunctional_product_group": 1,
    "multifunctional_product_groups": 16,
    "product_group": 182,
    "product_group_or_explicit_product_form": 187,
    "special_product_group": 34,
    "suspension_fluid_product_group": 1,
    "technical_fluid_product_group": 210
  },
  "normalized_output_sha256": "fe9dd647609f1e93e516a93ff9afc7dbfc2f65965e773409bdd752b5cd0a1f6d",
  "rights_review": "The official imprint permits informational organizational use when the copyright notice is retained and prohibits commercial use. Only attributed factual fields are republished; marketing descriptions are excluded and represented only by SHA-256 evidence hashes.",
  "publication_scope": "Product identity, region, group, specifications, approvals, recommendations and derived technical fields; no marketing descriptions or page layout."
}
